PX-8GVTDR-HR-HDRAM/src/main.v
// SPDX-License-Identifier: CERN-OHL-S-2.0
//
// This source file is part of Pheonix-HDRAM
// Licensed under the CERN-OHL-S v2 (https://cern-ohl.web.cern.ch).
// You may redistribute and modify this file under the terms of the CERN-OHL-S v2.

`timescale 1ns/1ps

module px_8gvtdr_hr_hdram #(
    parameter DQ_WIDTH = 16,
    parameter ADDR_WIDTH = 7,
    parameter BANK_WIDTH = 1, // 4 (Final)
    parameter DM_WIDTH = 2,
    parameter NUM_BANKS = (1<<BANK_WIDTH),
    parameter ROW_BITS = 3, // 14 (Final)
    parameter COL_BITS = 4, // 10 (Final)
    parameter ROW_POSE = 7, // Row Position End
    parameter COL_POSE = 4, // Column Position End
    parameter SIM_SIZE = NUM_BANKS*(1<<COL_BITS) // SIM
) (
    // Clocks
    input wire clk,
    input wire reset_n,

    // Control signals
    input wire cs_n,
    input wire ras_n,
    input wire cas_n,
    input wire we_n,
    input wire cke,
    input wire mddr_n, // Mode Double Data Rate (Active-Low)

    // Address
    input wire [ADDR_WIDTH-1:0] addr,
    input wire [BANK_WIDTH-1:0] ba,

    // Data
    inout wire [DQ_WIDTH-1:0] dq,
    input wire [DM_WIDTH-1:0] dm,
    output reg tdr_a, // TDR Active
    output reg async_bs, // Async Bit Sent
    input wire backn, // Bit 1 Acknowledged
    output reg barm // Bit Arm, 1 whenever bits have started being sent
);
    reg [DQ_WIDTH-1:0] mem [0:SIM_SIZE-1];

    reg async_bs_next;
    reg [DQ_WIDTH-1:0] dq_next; // Sync Precomputed data

    reg [DQ_WIDTH-1:0] dq_out;
    reg [DQ_WIDTH-1:0] dq_next1; // Async Precomputed Data
    reg dq_drive; // Controls when the chip drives the DQ

    reg [ROW_BITS-1:0] active_row [0:NUM_BANKS-1];
    reg row_open [0:NUM_BANKS-1];

    wire [ROW_BITS-1:0] row;
    wire [COL_BITS-1:0] col;

    assign row = addr[ROW_POSE-1:COL_POSE];
    assign col = addr[COL_POSE-1:0];
    assign dq = dq_drive ? dq_out : {DQ_WIDTH{1'bz}};

    // Timing
    integer trcd_count, trp_count, cas_delay;
    localparam trcd = 2, trp = 2, tcas = 2;

    // Triple Data Rate
    reg tdr_req;
    reg [2:0] bit_count;

    reg cas_fire;

    reg tdr_mode;

    integer i;
    integer w;
    always @(posedge clk or negedge reset_n) begin
        if (!reset_n) begin
            dq_out <= 0;
            trcd_count <= 0;
            trp_count <= 0;
            cas_delay <= 0;

            for (i = 0; i < NUM_BANKS; i=i+1) begin
                row_open[i] <= 1'b0;
                active_row[i] <= 0;
            end
        end else if (!cs_n) begin
            if (!ras_n && cas_n && we_n) begin // Active CMD
                row_open[ba] <= 1'b1;
                active_row[ba] <= row;
                trcd_count <= trcd; // start timing
            end else if (ras_n && !cas_n && we_n && row_open[ba] && trcd_count == 0) begin // Read CMD
                cas_delay <= tcas;
                dq_drive <= 0;
                bit_count <= 0;
            end else if (ras_n && !cas_n && !we_n && row_open[ba] && trcd_count == 0) begin // Write CMD
                dq_next = mem[{ba, row, col}];
                for (w = 0; w < (DQ_WIDTH/8); w=w+1)
                    if (!dm[w]) 
                        dq_next[w*8 +: 8] = dq[w*8 +: 8];
                mem[{ba, row, col}] <= dq_next;
            end else if (!ras_n && cas_n && !we_n) begin // Precharge CMD
                row_open[ba] <= 1'b0;
                trp_count <= trp;
            end else begin
                dq_drive <= 0;
            end
        end

        if (trcd_count > 0) trcd_count <= trcd_count - 1;
        if (trp_count > 0) trp_count <= trp_count - 1;

        cas_fire <= (cas_delay - 1 == 1);
        tdr_mode <= mddr_n;
        if (cas_delay > 0) begin
            cas_delay <= cas_delay - 1;
        end
    end

    always @(posedge clk or negedge reset_n) begin
        if (!reset_n) begin
            tdr_req <= 0;
            bit_count <= 0;
            dq_drive <= 0;
            async_bs <= 0;
            barm <= 0;
        end else if (cas_fire && row_open[ba]) begin
            dq_drive <= 1;
            dq_out <= mem[{ba, row, col}];
            bit_count <= 1;
            barm <= 1; 
            tdr_req = 1;
        end
    end

    always @(*) begin
        if (cas_fire && tdr_req && reset_n && mddr_n) begin
            dq_next = mem[{ba, row, col + 2'd1}];
            async_bs_next = 1;
            bit_count = 2;
            tdr_req = 0;
        end else if (reset_n && cas_delay == 0 && async_bs_next) begin
            if (backn) begin // Data is Acknowledged
                $display("Bit Ackn @%0t", $time);
                dq_out = dq_next;
                async_bs = async_bs_next;
                async_bs_next = 0;
            end
        end
    end

    always @(negedge clk or negedge reset_n) begin
        if (reset_n && async_bs)
            async_bs <= 0;

        if (!reset_n) begin
            tdr_a <= 0;
            barm <= 0;
        end else if (cas_fire && tdr_mode && backn) begin // TDR Mode
            tdr_a <= 0;

            if (tdr_req == 0 && bit_count > 1) begin // Send bit 3
                bit_count <= 3;
                dq_out <= mem[{ba, row, col + 2'd2}];
                tdr_a <= 1;
                dq_drive <= 0;
            end else begin // DO NOT SEND ANYTHING
                tdr_a <= 0;
                dq_drive <= 0;
            end

            barm <= 0;
        end else if (cas_fire && !tdr_mode) begin // DDR Mode, Send only bit 2
            tdr_a <= 0;
            bit_count <= 2;
            dq_out <= mem[{ba, row, col + 2'd1}];
            dq_drive <= 0;

            barm <= 0;
        end
    end
endmodule

PX-8GVTDR-HR-HDRAM/src/testers/main_t.v
// SPDX-License-Identifier: CERN-OHL-S-2.0
//
// This source file is part of Pheonix-HDRAM
// Licensed under the CERN-OHL-S v2 (https://cern-ohl.web.cern.ch).
// You may redistribute and modify this file under the terms of the CERN-OHL-S v2.

`timescale 1ns/1ps

module tb_px_8gvtdr_hr_hdram #(
    parameter DQ_WIDTH = 16,
    parameter ADDR_WIDTH = 7,
    parameter BANK_WIDTH = 1, // 4 (Final)
    parameter DM_WIDTH = 2,
    parameter NUM_BANKS = (1<<BANK_WIDTH),
    parameter ROW_BITS = 3, // 14 (Final)
    parameter COL_BITS = 4, // 10 (Final)
    parameter ROW_POSE = 7, // Row Position End
    parameter COL_POSE = 4, // Column Position End
    parameter SIM_SIZE = NUM_BANKS*(1<<COL_BITS) // SIM
);

    // Clock with jitter
    reg clk = 0;
    real base_period = 0.2; // 10.0=100 MHz 1.0=1 GHz 0.2=5GHz
    real jitter;

    always begin
        jitter = ($urandom_range(600) - 300) * 0.001; // +/- 300ps
        #((base_period/2.0) + jitter) clk = ~clk;
    end

    // Signals
    reg reset_n;
    reg cs_n, ras_n, cas_n, we_n, cke;
    reg [ADDR_WIDTH-1:0] addr;
    reg [BANK_WIDTH-1:0] ba;
    wire [DQ_WIDTH-1:0] dq;
    reg [DM_WIDTH-1:0] dm;

    wire tdr_a;
    wire async_bs;
    wire bit_arm;
    reg ddr_mode_n;
    reg bit_ackn;

    reg [DQ_WIDTH-1:0] dq_drv;
    reg dq_oe;
    assign dq = dq_oe ? dq_drv : {DQ_WIDTH{1'hz}};

    // DUT
    px_8gvtdr_hr_hdram dut (
        .clk(clk),
        .reset_n(reset_n),
        .cs_n(cs_n),
        .ras_n(ras_n),
        .cas_n(cas_n),
        .we_n(we_n),
        .cke(cke),
        .addr(addr),
        .ba(ba),
        .dq(dq),
        .dm(dm),
        .tdr_a(tdr_a),
        .async_bs(async_bs),
        .barm(bit_arm),
        .mddr_n(ddr_mode_n),
        .backn(bit_ackn)
    );

    // Golden memory
    reg [DQ_WIDTH-1:0] golden_mem [0:SIM_SIZE-1];

    // Reading TDR setup
    reg read_start;
    reg read_done;
    integer read_bursts;
    reg [DQ_WIDTH-1:0] read_samples [0:2];
    reg read_bit_armed;
    reg [BANK_WIDTH-1:0] read_bank;
    reg [COL_BITS-1:0] read_col;
    reg read_async_bit_done;

    always @(posedge clk) begin
        if (read_start && !read_done) begin
            #1;
            if (bit_arm && !read_bit_armed) begin
                read_samples[0] = dq;
                bit_ackn = 1;
                read_bit_armed = 1;
                read_bursts = 1;
                $display("Debug: Rising edge burst %0d -> bank=%0d col=%0d data=0x%h @%0t", read_bursts, read_bank, read_col, read_samples[0], $time);
            end
        end
    end

    always @(negedge clk) begin
        if (read_start && !read_done) begin
            #1;
            if (read_bit_armed && tdr_a) begin
                read_samples[2] = dq;
                bit_ackn = 0;
                read_bit_armed = 0;
                read_bursts = read_bursts + 1;
                read_done = 1;
                $display("Debug: Falling edge burst %0d -> bank=%0d col=%0d data=0x%h mode=TDR @%0t", read_bursts, read_bank, read_col, read_samples[2], $time);
            end else if (read_bit_armed && !tdr_a) begin
                read_bursts = read_bursts + 1;
                read_bit_armed = 0;
                read_done = 1;
                $display("Debug: Falling edge -> bank=%0d col=%0d mode=DDR @%0t", read_bank, read_col, $time);
            end
        end
    end

    always @(*) begin
        if (read_start && !read_done) begin
            if (read_bit_armed && async_bs && !read_async_bit_done) begin
                read_samples[1] = dq;
                read_bursts = read_bursts + 1;
                read_async_bit_done = 1;
                $display("Debug: Async burst 50d -> bank=%0d col=%0d data=0x%h @%0t", read_bursts, read_bank, read_col, read_samples[1], $time);
            end
        end
    end

    // Reset
    initial begin
        reset_n = 0;
        cs_n = 1; ras_n = 1; cas_n = 1; we_n = 1; cke = 1;
        dq_oe = 0; dm = 0; addr = 0; ba = 0;

        repeat (8) @(posedge clk);
        reset_n = 1;
        repeat ($urandom_range(2,10)) @(posedge clk);
    end

    // IC commands
    task activate(input [BANK_WIDTH-1:0] bank, input [ROW_BITS-1:0] row);
        begin
            @(posedge clk);
            ba <= bank;
            addr <= row;
            cs_n <= 0; ras_n <= 0; cas_n <= 1; we_n <= 1;
            @(posedge clk);
            cs_n <= 1; ras_n <= 1;
            $display("Debug: Bank %0d Row %0d has been activated!", bank, row);
        end
    endtask

    task write_mem(input [BANK_WIDTH-1:0] bank, input [ROW_BITS-1:0] row, input [COL_BITS-1:0] col, input [DQ_WIDTH-1:0] data);
        begin
            repeat ($urandom_range(1,3)) @(posedge clk);
            golden_mem[{bank,col}] = data;

            @(posedge clk);
            ba <= bank; addr <= col; cs_n <= 0; ras_n <= 1; cas_n <= 0; we_n <= 0;
            dq_drv <= data; dq_oe <= 1;
            @(posedge clk);
            dq_oe <= 0; cs_n <= 1; cas_n <= 1; we_n <= 1;
            $display("Debug: Written data 0x%h @%0t", data, $time);
        end
    endtask

    task read_mem(input [BANK_WIDTH-1:0] bank, input [ROW_BITS-1:0] row, input [COL_BITS-1:0] col);
        begin
            repeat ($urandom_range(1,4)) @(posedge clk);

            @(posedge clk);
            ba <= bank; addr <= col; cs_n <= 0; ras_n <= 1; cas_n <= 0; we_n <= 1; ddr_mode_n <= 1;
            @(posedge clk);
            cs_n <= 1; cas_n <= 1;

            read_samples[0] = 0;
            read_samples[1] = 0;
            read_samples[2] = 0;
            bit_ackn = 0;
            read_bursts = 0;
            read_bit_armed = 0;
            read_done = 0;
            read_bank = bank;
            read_col = col;
            read_start = 1;
            read_async_bit_done = 0;

            // Wait for TDR beats
            wait (read_done || read_bursts >= 3);

            read_start = 0;
            read_done = 0;
            bit_ackn = 0;
            read_bursts = 0;
            read_bit_armed = 0;

            if (read_samples[0] !== golden_mem[{bank,row,col}]) begin
                $display("Error: Read mismatch bank=%0d row=%0d col=%0d exp=0x%h got=0x%h @%0t", bank, row, col, golden_mem[{bank,row,col}], read_samples[0], $time);
                $stop;
            end else begin
                $display("Ok: Read bank=%0d col=%0d data=0x%h", bank, col, read_samples[0]);
            end
        end
    endtask

    task read_mem_tdr(input [BANK_WIDTH-1:0] bank, input [ROW_BITS-1:0] row, input [COL_BITS-1:0] col);
        begin
            repeat ($urandom_range(1,4)) @(posedge clk);

            @(posedge clk);
            ba <= bank; addr <= col; cs_n <= 0; ras_n <= 1; cas_n <= 0; we_n <= 1; ddr_mode_n <= 1;
            @(posedge clk);
            cs_n <= 1; cas_n <= 1;

            read_samples[0] = 0;
            read_samples[1] = 0;
            read_samples[2] = 0;
            bit_ackn = 0;
            read_bursts = 0;
            read_bit_armed = 0;
            read_done = 0;
            read_bank = bank;
            read_col = col;
            read_start = 1;
            read_async_bit_done = 0;

            // Wait for TDR beats
            wait (read_done || read_bursts >= 3);

            read_start = 0;
            read_done = 0;
            bit_ackn = 0;
            read_bursts = 0;
            read_bit_armed = 0;

            if (read_samples[0] !== golden_mem[{bank,row,col}] || read_samples[1] !== golden_mem[{bank,row,col+2'd1}] || read_samples[2] !== golden_mem[{bank,row,col+2'd2}]) begin
                $display("Error: Read mismatch bank=%0d row=%0d col=%0d exp=0x%h%h%h got=0x%h%h%h @%0t", bank, row, col, golden_mem[{bank,row,col}],
                    golden_mem[{bank,row,col+2'd1}], golden_mem[{bank,row,col+2'd2}], read_samples[0], read_samples[1], read_samples[2], $time);
                $stop;
            end else begin
                $display("Ok: Read bank=%0d col=%0d data=0x%h%h%h", bank, col, read_samples[0], read_samples[1], read_samples[2]);
            end
        end
    endtask

    task precharge(input [BANK_WIDTH-1:0] bank);
        begin
            @(posedge clk);
            ba <= bank; cs_n <= 0; ras_n <= 0; cas_n <= 1; we_n <= 0;
            @(posedge clk);
            cs_n <= 1; ras_n <= 1; we_n <= 1;
        end
    endtask

    // Stress test
    integer i;
    reg [DQ_WIDTH-1:0] data;

    initial begin
        @(posedge reset_n);
        for (i = 0; i < 50; i=i+1) begin
            ba = $urandom_range(0,BANK_WIDTH-1);
            addr = $urandom_range(0,127);
            data = $random;

            activate(ba, addr[ROW_POSE-1:COL_POSE]);
            write_mem(ba, addr[ROW_POSE-1:COL_POSE], addr[COL_POSE-1:0], data);
            read_mem(ba, addr[ROW_POSE-1:COL_POSE], addr[COL_POSE-1:0]);
            read_mem_tdr(ba, addr[ROW_POSE-1:COL_POSE], addr[COL_POSE-1:0]);
            precharge(ba);

            repeat ($urandom_range(2,8)) @(posedge clk);
        end
        $display("Success: All Tests Passed!");
        #100 $finish;
    end

    // Waveform
    initial begin
        $dumpfile("tests/waveforms/main_t.vcd");
        $dumpvars(0, tb_px_8gvtdr_hr_hdram);
    end

endmodule

PX-8GVTDR-HR-HDRAM/tests/waveforms/main_t.vcd
$date
	Tue Jan  6 21:36:25 2026
$end
$version
	Icarus Verilog
$end
$timescale
	1ps
$end
$scope module tb_px_8gvtdr_hr_hdram $end
$var wire 16 ! dq [15:0] $end
$var wire 1 " tdr_a $end
$var wire 1 # bit_arm $end
$var wire 1 $ async_bs $end
$var parameter 32 % ADDR_WIDTH $end
$var parameter 32 & BANK_WIDTH $end
$var parameter 32 ' COL_BITS $end
$var parameter 32 ( COL_POSE $end
$var parameter 32 ) DM_WIDTH $end
$var parameter 32 * DQ_WIDTH $end
$var parameter 33 + NUM_BANKS $end
$var parameter 32 , ROW_BITS $end
$var parameter 32 - ROW_POSE $end
$var parameter 69 . SIM_SIZE $end
$var reg 7 / addr [6:0] $end
$var reg 1 0 ba $end
$var reg 1 1 bit_ackn $end
$var reg 1 2 cas_n $end
$var reg 1 3 cke $end
$var reg 1 4 clk $end
$var reg 1 5 cs_n $end
$var reg 16 6 data [15:0] $end
$var reg 1 7 ddr_mode_n $end
$var reg 2 8 dm [1:0] $end
$var reg 16 9 dq_drv [15:0] $end
$var reg 1 : dq_oe $end
$var reg 1 ; ras_n $end
$var reg 1 < read_async_bit_done $end
$var reg 1 = read_bank $end
$var reg 1 > read_bit_armed $end
$var reg 4 ? read_col [3:0] $end
$var reg 1 @ read_done $end
$var reg 1 A read_start $end
$var reg 1 B reset_n $end
$var reg 1 C we_n $end
$var real 1 D base_period $end
$var integer 32 E i [31:0] $end
$var real 1 F jitter $end
$var integer 32 G read_bursts [31:0] $end
$scope module dut $end
$var wire 7 H addr [6:0] $end
$var wire 1 0 ba $end
$var wire 1 1 backn $end
$var wire 1 2 cas_n $end
$var wire 1 3 cke $end
$var wire 1 4 clk $end
$var wire 1 5 cs_n $end
$var wire 2 I dm [1:0] $end
$var wire 16 J dq [15:0] $end
$var wire 1 7 mddr_n $end
$var wire 1 ; ras_n $end
$var wire 1 B reset_n $end
$var wire 1 C we_n $end
$var wire 3 K row [2:0] $end
$var wire 4 L col [3:0] $end
$var parameter 32 M ADDR_WIDTH $end
$var parameter 32 N BANK_WIDTH $end
$var parameter 32 O COL_BITS $end
$var parameter 32 P COL_POSE $end
$var parameter 32 Q DM_WIDTH $end
$var parameter 32 R DQ_WIDTH $end
$var parameter 33 S NUM_BANKS $end
$var parameter 32 T ROW_BITS $end
$var parameter 32 U ROW_POSE $end
$var parameter 69 V SIM_SIZE $end
$var parameter 32 W tcas $end
$var parameter 32 X trcd $end
$var parameter 32 Y trp $end
$var reg 1 $ async_bs $end
$var reg 1 Z async_bs_next $end
$var reg 1 # barm $end
$var reg 3 [ bit_count [2:0] $end
$var reg 1 \ cas_fire $end
$var reg 1 ] dq_drive $end
$var reg 16 ^ dq_next [15:0] $end
$var reg 16 _ dq_out [15:0] $end
$var reg 1 " tdr_a $end
$var reg 1 ` tdr_mode $end
$var reg 1 a tdr_req $end
$var integer 32 b cas_delay [31:0] $end
$var integer 32 c i [31:0] $end
$var integer 32 d trcd_count [31:0] $end
$var integer 32 e trp_count [31:0] $end
$var integer 32 f w [31:0] $end
$upscope $end
$scope task activate $end
$var reg 1 g bank $end
$var reg 3 h row [2:0] $end
$upscope $end
$scope task precharge $end
$var reg 1 i bank $end
$upscope $end
$scope task read_mem $end
$var reg 1 j bank $end
$var reg 4 k col [3:0] $end
$var reg 3 l row [2:0] $end
$upscope $end
$scope task read_mem_tdr $end
$var reg 1 m bank $end
$var reg 4 n col [3:0] $end
$var reg 3 o row [2:0] $end
$upscope $end
$scope task write_mem $end
$var reg 1 p bank $end
$var reg 4 q col [3:0] $end
$var reg 16 r data [15:0] $end
$var reg 3 s row [2:0] $end
$upscope $end
$upscope $end
$enddefinitions $end
$comment Show the parameter values. $end
$dumpall
b10 Y
b10 X
b10 W
b100000 V
b111 U
b11 T
b10 S
b10000 R
b10 Q
b100 P
b100 O
b1 N
b111 M
b100000 .
b111 -
b11 ,
b10 +
b10000 *
b10 )
b100 (
b100 '
b1 &
b111 %
$end
#0
$dumpvars
bx s
bx r
bx q
xp
bx o
bx n
xm
bx l
bx k
xj
xi
bx h
xg
bx f
b0 e
b0 d
b10 c
b0 b
0a
x`
b0 _
bx ^
0]
x\
b0 [
xZ
b0 L
b0 K
bz J
b0 I
b0 H
bx G
r0.042 F
bx E
r0.2 D
1C
0B
xA
x@
bx ?
x>
x=
x<
1;
0:
bx 9
b0 8
x7
bx 6
15
04
13
12
x1
00
b0 /
0$
0#
0"
bz !
$end
#142
0\
b10 c
r4294967.147 F
14
#4294967389
r4294967.006 F
04
#8589934495
b10 c
r4294967.113 F
14
#12884901708
r0.016 F
04
#12884901824
b10 c
r0.166 F
14
#12884902090
r4294967.115 F
04
#17179869305
b10 c
r4294967.017 F
14
#21474836422
r0.002 F
04
#21474836524
b10 c
r0.016 F
14
#21474836640
r0.139 F
04
#21474836879
b10 c
r0.07200000000000001 F
14
#21474837051
r0.279 F
04
#21474837430
b10 c
r0.165 F
14
#21474837695
r0.293 F
04
#21474838088
b10 K
b1010 L
b10 h
0g
b11010100100100 6
b101010 /
b101010 H
b0 E
1B
r4294967.228 F
14
#25769805416
r0.269 F
04
#25769805785
b0 K
b10 L
0;
05
b10 /
b10 H
r4294967.136 F
14
#30064773021
r4294967.017 F
04
#34359740138
b10 d
1;
15
b11010100100100 r
b10 q
b0 s
0p
r0.169 F
14
#34359740407
r4294967.238 F
04
#38654707745
b1 d
r4294967.268 F
14
#42949675113
r4294967.227 F
04
#47244642440
b0 d
r0.109 F
14
#47244642649
r4294967.217 F
04
#51539609966
r4294967.049 F
14
#55834577115
r4294967.114 F
04
#60129544329
b11010100100100 !
b11010100100100 J
1:
b11010100100100 9
0C
02
05
r4294967.113 F
14
#64424511542
r0.013 F
04
#64424511655
bz !
bz J
1C
12
15
0:
b11010100100100 ^
b10 f
b10 k
b0 l
0j
r4294967.146 F
14
#68719478901
r0.201 F
04
#68719479202
r4294967.18 F
14
#73014446482
r4294967.172 F
04
#77309413754
r4294967.018 F
14
#81604380872
r4294967.011 F
04
#85899347983
r4294967.093 F
14
#90194315176
r0.126 F
04
#90194315402
17
02
05
r4294967.246 F
14
#94489282748
r4294966.998 F
04
#98784249846
1`
b10 b
12
15
0<
1A
b10 ?
0=
0@
0>
b0 G
01
r4294967.201 F
14
#103079217147
r0.035 F
04
#103079217282
b1 b
1\
r4294967.239 F
14
#107374184621
r0.041 F
04
#107374184762
b11010100100100 !
b11010100100100 J
b0 b
0\
1#
b11010100100100 _
1]
b1 [
1Z
bx ^
0a
r0.012 F
14
#107374184874
r4294967.234 F
04
#107374185762
1<
bx !
bx J
0Z
1$
bx _
b10 G
1>
11
#111669152208
r4294967.066 F
14
#115964119374
0$
r0.285 F
04
#115964119759
r0.162 F
14
#115964120021
r0.077 F
04
#115964120198
r4294967.25 F
14
#115964120374
b10 n
b0 o
0m
01
0A
0@
0>
b0 G
#115964120759
b1 G
1>
11
#120259087548
r4294967.156 F
04
#124554054804
r0.276 F
14
#124554055180
r0.214 F
04
#124554055494
r0.233 F
14
#124554055827
r0.204 F
04
#124554056131
r4294967.217 F
14
#128849023448
r0.049 F
04
#128849023597
02
05
r4294967.009000001 F
14
#133143990706
r4294967.128 F
04
#137438957934
bz !
bz J
b0 [
0]
b10 b
12
15
0<
1A
0>
b0 G
01
r0.157 F
14
#137438958191
r0.094 F
04
#137438958385
b1 b
1\
r4294967.065 F
14
#137438959385
b1 G
1>
11
#141733925550
0#
r0.068 F
04
#141733925718
1<
b10 G
1$
bx !
bx J
b0 b
0\
1#
bx _
1]
b1 [
0Z
0a
r4294967.144 F
14
