PX-8GVTDR-HR-HDRAM/src/main.v
// SPDX-License-Identifier: CERN-OHL-S-2.0
//
// This source file is part of Pheonix-HDRAM
// Licensed under the CERN-OHL-S v2 (https://cern-ohl.web.cern.ch).
// You may redistribute and modify this file under the terms of the CERN-OHL-S v2.

module px_8gvtdr_hr_hdram #(
    parameter DQ_WIDTH = 16,
    parameter ADDR_WIDTH = 24,
    parameter BANK_WIDTH = 4,
    parameter DM_WIDTH = 2,
    parameter NUM_BANKS = (1<<BANK_WIDTH),
    parameter ROW_BITS = 14,
    parameter COL_BITS = 10,
    parameter SIM_SIZE = NUM_BANKS*(1<<COL_BITS) // SIM
) (
    // Clocks
    input wire clk,
    input wire reset_n,

    // Control signals
    input wire cs_n,
    input wire ras_n,
    input wire cas_n,
    input wire we_n,
    input wire cke,

    // Address
    input wire [ADDR_WIDTH-1:0] addr,
    input wire [BANK_WIDTH-1:0] ba,

    // Data
    inout wire [DQ_WIDTH-1:0] dq,
    input wire [DM_WIDTH-1:0] dm,
    output reg tdr_a, // TDR Active
    output reg async_bs, // Async Bit Sent
    output reg barm // Bit Arm, 1 whenever bits have started being sent
);
    reg [DQ_WIDTH-1:0] mem [0:SIM_SIZE-1];

    reg async_bs_next;
    reg [DQ_WIDTH-1:0] dq_next; // Sync Precomputed data

    reg [DQ_WIDTH-1:0] dq_out;
    reg [DQ_WIDTH-1:0] dq_next1; // Async Precomputed Data
    reg dq_drive; // Controls when the chip drives the DQ

    reg [ROW_BITS-1:0] active_row [0:NUM_BANKS-1];
    reg row_open [0:NUM_BANKS-1];

    assign dq = dq_drive ? dq_out : {DQ_WIDTH{1'bz}};

    // Timing
    integer trcd_count, trp_count, cas_delay;
    localparam trcd = 2, trp = 2, tcas = 2;

    // Triple Data Rate
    reg tdr_req;
    reg [2:0] bit_count;

    reg cas_fire;

    integer i;
    integer w;
    always @(posedge clk or negedge reset_n) begin
        if (!reset_n) begin
            dq_out <= 0;
            trcd_count <= 0;
            trp_count <= 0;
            cas_delay <= 0;

            for (i = 0; i < NUM_BANKS; i=i+1) begin
                row_open[i] <= 1'b0;
                active_row[i] <= 0;
            end
        end else if (!cs_n) begin
            if (!ras_n && cas_n && we_n) begin // Active CMD
                row_open[ba] <= 1'b1;
                active_row[ba] <= addr[ROW_BITS-1:0];
                trcd_count <= trcd; // start timing
            end else if (ras_n && !cas_n && we_n && row_open[ba] && trcd_count == 0) begin // Read CMD
                cas_delay <= tcas;
                dq_drive <= 0;
                bit_count <= 0;
            end else if (ras_n && !cas_n && !we_n && row_open[ba] && trcd_count == 0) begin // Write CMD
                for (w = 0; w < (DQ_WIDTH/8); w=w+1)
                    if (!dm[w]) 
                        mem[{ba, addr[COL_BITS-1:0]}] <= dq[w*8 +: 8];
            end else if (!ras_n && cas_n && !we_n) begin // Precharge CMD
                row_open[ba] <= 1'b0;
                trp_count <= trp;
            end else begin
                dq_drive <= 0;
            end
        end

        if (trcd_count > 0) trcd_count <= trcd_count - 1;
        if (trp_count > 0) trp_count <= trp_count - 1;

        cas_fire <= (cas_delay - 1 == 1);
        if (cas_delay > 0) begin
            cas_delay <= cas_delay - 1;
        end
    end

    always @(posedge clk or negedge reset_n) begin
        if (!reset_n) begin
            tdr_req <= 0;
            bit_count <= 0;
            dq_drive <= 0;
            async_bs <= 0;
            barm <= 0;
        end else if (cas_fire && row_open[ba]) begin
            dq_drive <= 1;
            dq_out <= mem[{ba, addr[COL_BITS-1:0]}];
            bit_count <= 1;
            barm <= 1;
            dq_next = mem[{ba, addr[COL_BITS-1:0]}];
            $display("Sync bit: 0x%h", dq_next);
            tdr_req = 1;
        end
    end

    always @(*) begin
        if (cas_fire && tdr_req && reset_n) begin
            dq_next1 = mem[{ba, addr[COL_BITS-1:0]}];
            $display("Async Bit: 0x%h", dq_next1);
            async_bs_next = 1;
            bit_count = 2;
            tdr_req = 0;
        end else if (reset_n && cas_delay == 0 && async_bs_next) begin
            if (dq == dq_next) begin // Data is stable and sent
                dq_out = dq_next1;
                async_bs = async_bs_next;
                async_bs_next = 0;
            end
        end
    end

    always @(negedge clk or negedge reset_n) begin
        if (reset_n && async_bs)
            async_bs <= 0;

        if (!reset_n) begin
            tdr_a <= 0;
        end else if (cas_fire) begin
            tdr_a <= 0;

            if (tdr_req == 0 && bit_count > 1) begin // Send bit 3
                bit_count <= 3;
                dq_out <= mem[{ba, addr[COL_BITS-1:0]}];
                tdr_a <= 1;
                dq_drive <= 0;
            end else if (tdr_req == 1 && bit_count >= 1) begin
                tdr_a <= 0;
                dq_drive <= 0;
            end

            barm <= 0;
        end
    end
endmodule

PX-8GVTDR-HR-HDRAM/src/testers/main_t.v
// SPDX-License-Identifier: CERN-OHL-S-2.0
//
// This source file is part of Pheonix-HDRAM
// Licensed under the CERN-OHL-S v2 (https://cern-ohl.web.cern.ch).
// You may redistribute and modify this file under the terms of the CERN-OHL-S v2.

`timescale 1ns/1ps

module tb_px_8gvtdr_hr_hdram;

    // Clock with jitter
    reg clk = 0;
    real base_period = 10.0; // 100 MHz
    real jitter;

    always begin
        jitter = ($urandom_range(-300,300)) * 0.001; // +/- 0.3ns
        #(base_period/2.0 + jitter) clk = ~clk;
    end

    // Signals
    reg reset_n;
    reg cs_n, ras_n, cas_n, we_n, cke;
    reg [23:0] addr;
    reg [3:0] ba;
    wire [15:0] dq;
    reg [1:0] dm;

    wire tdr_a;
    wire async_bs;
    wire bit_arm;

    reg [15:0] dq_drv;
    reg dq_oe;
    assign dq = dq_oe ? dq_drv : 16'hzzzz;

    // DUT
    px_8gvtdr_hr_hdram dut (
        .clk(clk),
        .reset_n(reset_n),
        .cs_n(cs_n),
        .ras_n(ras_n),
        .cas_n(cas_n),
        .we_n(we_n),
        .cke(cke),
        .addr(addr),
        .ba(ba),
        .dq(dq),
        .dm(dm),
        .tdr_a(tdr_a),
        .async_bs(async_bs),
        .barm(bit_arm)
    );

    // Golden memory
    reg [15:0] golden_mem [0:4095];

    // Reset
    initial begin
        reset_n = 0;
        cs_n = 1; ras_n = 1; cas_n = 1; we_n = 1; cke = 1;
        dq_oe = 0; dm = 0; addr = 0; ba = 0;

        repeat (8) @(posedge clk);
        reset_n = 1;
        repeat ($urandom_range(2,10)) @(posedge clk);
    end

    // IC commands
    task activate(input [3:0] bank, input [13:0] row);
        begin
            @(posedge clk);
            ba <= bank;
            addr <= row;
            cs_n <= 0; ras_n <= 0; cas_n <= 1; we_n <= 1;
            @(posedge clk);
            cs_n <= 1; ras_n <= 1;
            $display("Debug: Bank %0d Row %0d has been activated!", bank, row);
        end
    endtask

    task write_mem(input [3:0] bank, input [9:0] col, input [15:0] data);
        begin
            repeat ($urandom_range(1,3)) @(posedge clk);
            golden_mem[{bank,col}] = data;

            @(posedge clk);
            ba <= bank; addr <= col; cs_n <= 0; ras_n <= 1; cas_n <= 0; we_n <= 0;
            dq_drv <= data; dq_oe <= 1;
            @(posedge clk);
            dq_oe <= 0; cs_n <= 1; cas_n <= 1; we_n <= 1;
            $display("Debug: Written data 0x%h @%0t", data, $time);
        end
    endtask

    task read_mem(input [3:0] bank, input [9:0] col);
        reg [15:0] sampled;
        integer beat;
        reg bit_armed;
        begin
            repeat ($urandom_range(1,4)) @(posedge clk);

            @(posedge clk);
            ba <= bank; addr <= col; cs_n <= 0; ras_n <= 1; cas_n <= 0; we_n <= 1;
            @(posedge clk);
            cs_n <= 1; cas_n <= 1;

            beat = 0;
            sampled = 0;
            bit_armed = 0;

            // Wait for TDR beats
            while (beat < 3) begin
                // Async Sampling
                if (async_bs && bit_armed) begin
                    sampled = dq;
                    $display("Debug: Async beat 50d -> bank=%0d col=%0d data=0x%h @%0t", beat, bank, col, sampled, $time);
                    beat = beat + 1;
                end

                // Rising edge sampling
                @(posedge clk);
                if (bit_arm && !bit_armed) begin
                    sampled = dq;
                    $display("Debug: Rising edge beat %0d -> bank=%0d col=%0d data=0x%h @%0t", beat, bank, col, sampled, $time);
                    beat = beat + 1;
                    bit_armed = 1;
                end

                // Falling edge sampling
                @(negedge clk);
                if (tdr_a && bit_armed) begin
                    sampled = dq;
                    $display("Debug: Falling edge beat %0d -> bank=%0d col=%0d data=0x%h @%0t", beat, bank, col, sampled, $time);
                    beat = beat + 1;
                end else if (bit_armed) begin
                    bit_armed = 0;
                end
            end

            if (sampled !== golden_mem[{bank,col}]) begin
                $display("Error: Read mismatch bank=%0d col=%0d exp=0x%h got=0x%h @%0t", bank, col, golden_mem[{bank,col}], sampled, $time);
                $stop;
            end else begin
                $display("Ok: Read bank=%0d col=%0d data=0x%h", bank, col, sampled);
            end
        end
    endtask

    task precharge(input [3:0] bank);
        begin
            @(posedge clk);
            ba <= bank; cs_n <= 0; ras_n <= 0; cas_n <= 1; we_n <= 0;
            @(posedge clk);
            cs_n <= 1; ras_n <= 1; we_n <= 1;
        end
    endtask

    // Stress test
    integer i;
    reg [15:0] data;

    initial begin
        @(posedge reset_n);
        for (i = 0; i < 50; i=i+1) begin
            ba = $urandom_range(0,3);
            addr = $urandom_range(0,1023);
            data = $random;

            activate(ba, addr[13:0]);
            write_mem(ba, addr[9:0], data);
            read_mem(ba, addr[9:0]);
            precharge(ba);

            repeat ($urandom_range(2,8)) @(posedge clk);
        end
        $display("Success: All Tests Passed!");
        #100 $finish;
    end

    // Waveform
    initial begin
        $dumpfile("tests/waveforms/main_t.vcd");
        $dumpvars(0, tb_px_8gvtdr_hr_hdram);
    end

endmodule

PX-8GVTDR-HR-HDRAM/tests/waveforms/main_t.vcd
$date
	Sun Jan  4 21:25:16 2026
$end
$version
	Icarus Verilog
$end
$timescale
	1ps
$end
$scope module tb_px_8gvtdr_hr_hdram $end
$var wire 16 ! dq [15:0] $end
$var wire 1 " tdr_a $end
$var wire 1 # bit_arm $end
$var wire 1 $ async_bs $end
$var reg 24 % addr [23:0] $end
$var reg 4 & ba [3:0] $end
$var reg 1 ' cas_n $end
$var reg 1 ( cke $end
$var reg 1 ) clk $end
$var reg 1 * cs_n $end
$var reg 16 + data [15:0] $end
$var reg 2 , dm [1:0] $end
$var reg 16 - dq_drv [15:0] $end
$var reg 1 . dq_oe $end
$var reg 1 / ras_n $end
$var reg 1 0 reset_n $end
$var reg 1 1 we_n $end
$var real 1 2 base_period $end
$var integer 32 3 i [31:0] $end
$var real 1 4 jitter $end
$scope module dut $end
$var wire 24 5 addr [23:0] $end
$var wire 4 6 ba [3:0] $end
$var wire 1 ' cas_n $end
$var wire 1 ( cke $end
$var wire 1 ) clk $end
$var wire 1 * cs_n $end
$var wire 2 7 dm [1:0] $end
$var wire 16 8 dq [15:0] $end
$var wire 1 / ras_n $end
$var wire 1 0 reset_n $end
$var wire 1 1 we_n $end
$var parameter 32 9 ADDR_WIDTH $end
$var parameter 32 : BANK_WIDTH $end
$var parameter 32 ; COL_BITS $end
$var parameter 32 < DM_WIDTH $end
$var parameter 32 = DQ_WIDTH $end
$var parameter 36 > NUM_BANKS $end
$var parameter 32 ? ROW_BITS $end
$var parameter 32 @ SIM_SIZE $end
$var parameter 32 A tcas $end
$var parameter 32 B trcd $end
$var parameter 32 C trp $end
$var reg 1 $ async_bs $end
$var reg 1 D async_bs_next $end
$var reg 1 # barm $end
$var reg 3 E bit_count [2:0] $end
$var reg 1 F cas_fire $end
$var reg 1 G dq_drive $end
$var reg 16 H dq_next [15:0] $end
$var reg 16 I dq_next1 [15:0] $end
$var reg 16 J dq_out [15:0] $end
$var reg 1 " tdr_a $end
$var reg 1 K tdr_req $end
$var integer 32 L cas_delay [31:0] $end
$var integer 32 M i [31:0] $end
$var integer 32 N trcd_count [31:0] $end
$var integer 32 O trp_count [31:0] $end
$var integer 32 P w [31:0] $end
$upscope $end
$scope task activate $end
$var reg 4 Q bank [3:0] $end
$var reg 14 R row [13:0] $end
$upscope $end
$scope task precharge $end
$var reg 4 S bank [3:0] $end
$upscope $end
$scope task read_mem $end
$var reg 4 T bank [3:0] $end
$var reg 1 U bit_armed $end
$var reg 10 V col [9:0] $end
$var reg 16 W sampled [15:0] $end
$var integer 32 X beat [31:0] $end
$upscope $end
$scope task write_mem $end
$var reg 4 Y bank [3:0] $end
$var reg 10 Z col [9:0] $end
$var reg 16 [ data [15:0] $end
$upscope $end
$upscope $end
$enddefinitions $end
$comment Show the parameter values. $end
$dumpall
b10 C
b10 B
b10 A
b1000000000000 @
b1110 ?
b10000 >
b10000 =
b10 <
b1010 ;
b100 :
b11000 9
$end
#0
$dumpvars
bx [
bx Z
bx Y
bx X
bx W
bx V
xU
bx T
bx S
bx R
bx Q
bx P
b0 O
b0 N
b10000 M
b0 L
0K
b0 J
bx I
bx H
0G
xF
b0 E
xD
bz 8
b0 7
b0 6
b0 5
r2450863.354 4
bx 3
r10 2
11
00
1/
0.
bx -
b0 ,
bx +
1*
0)
1(
1'
b0 &
b0 %
0$
0#
0"
bz !
$end
#2450868354
0F
b10000 M
r1082744.598 4
1)
#3533617952
r75814.698 4
0)
#3609437650
b10000 M
r837834.523 4
1)
#4447277173
r2260302.59 4
0)
#6707584763
b10000 M
r3336542.44 4
1)
#10044132203
r851608.858 4
0)
#10895746061
b10000 M
r154620.712 4
1)
#11050371773
r2163467.008 4
0)
#13213843781
b10000 M
r2262289.662 4
1)
#15476138443
r3139694.828 4
0)
#18615838271
b10000 M
r2660093.174 4
1)
#21275936445
r4141111 4
0)
#25417052445
b10000 M
r3324901.096 4
1)
#28741958541
r4244498.646 4
0)
#32986462187
b1111001010 R
b1 Q
b11010100100100 +
b1111001010 %
b1111001010 5
b1 &
b1 6
b0 3
10
r1664558.346 4
1)
#34651025533
r1003647.767 4
0)
#35654678300
0/
0*
r154326.824 4
1)
#35809010124
r3354188.52 4
0)
#39163203644
b10 N
1/
1*
b11010100100100 [
b1111001010 Z
b1 Y
r4180699.351 4
1)
#43343907995
r1946188.548 4
0)
#45290101543
b1 N
r1657425.674 4
1)
#46947532217
r2925021.424 4
0)
#49872558641
b0 N
r1586374.923 4
1)
#51458938564
r380328.228 4
0)
#51839271792
b11010100100100 !
b11010100100100 8
1.
b11010100100100 -
01
0'
0*
r849815.322 4
1)
#52689092114
r837772.059 4
0)
#53526869173
bz !
bz 8
11
1'
1*
0.
b10 P
b1111001010 V
b1 T
r2238940.926 4
1)
#55765815099
r2422481.146 4
0)
#58188301245
r3581428.963 4
1)
#61769735208
r1322044.689 4
0)
#63091784897
r1260404.498 4
1)
#64352194395
r159627.56 4
0)
#64511826955
0'
0*
r112998.697 4
1)
#64624830652
r698865.437 4
0)
#65323701089
b10 L
1'
1*
0U
b0 W
b0 X
r3047152.878 4
1)
#68370858967
r1789274.887 4
0)
#70160138854
b1 L
1F
r18303.787 4
1)
#70178447641
r1465270.03 4
0)
#71643722671
1$
b110101 !
b110101 8
b0 L
0F
1#
b110101 J
1G
b1 E
0D
b110101 I
0K
b110101 H
r2399135.995 4
1)
#74042863666
0$
r1740993.288 4
0)
#75783861954
1U
b1 X
b110101 W
r2441365.754 4
1)
#78225232708
0U
r2231985.406 4
0)
#80457223114
1U
b10 X
r1702038.281 4
1)
#82159266395
0U
r506547.489 4
0)
#82665818884
1U
b11 X
r4184390.871 4
1)
