PX-8GVTDR-HR-HDRAM/src/main.v
// SPDX-License-Identifier: CERN-OHL-S-2.0
//
// This source file is part of Pheonix-HDRAM
// Licensed under the CERN-OHL-S v2 (https://cern-ohl.web.cern.ch).
// You may redistribute and modify this file under the terms of the CERN-OHL-S v2.

module px_8gvtdr_hr_hdram #(
    parameter DQ_WIDTH = 16,
    parameter ADDR_WIDTH = 7,
    parameter BANK_WIDTH = 1, // 4 (Final)
    parameter DM_WIDTH = 2,
    parameter NUM_BANKS = (1<<BANK_WIDTH),
    parameter ROW_BITS = 3, // 14 (Final)
    parameter COL_BITS = 4, // 10 (Final)
    parameter ROW_POSE = 7, // Row Position End
    parameter COL_POSE = 4, // Column Position End
    parameter SIM_SIZE = NUM_BANKS*(1<<COL_BITS) // SIM
) (
    // Clocks
    input wire clk,
    input wire reset_n,

    // Control signals
    input wire cs_n,
    input wire ras_n,
    input wire cas_n,
    input wire we_n,
    input wire cke,
    input wire mddr_n, // Mode Double Data Rate (Active-Low)

    // Address
    input wire [ADDR_WIDTH-1:0] addr,
    input wire [BANK_WIDTH-1:0] ba,

    // Data
    inout wire [DQ_WIDTH-1:0] dq,
    input wire [DM_WIDTH-1:0] dm,
    output reg tdr_a, // TDR Active
    output reg async_bs, // Async Bit Sent
    input wire backn, // Bit 1 Acknowledged
    output reg barm // Bit Arm, 1 whenever bits have started being sent
);
    reg [DQ_WIDTH-1:0] mem [0:SIM_SIZE-1];

    reg async_bs_next;
    reg [DQ_WIDTH-1:0] dq_next; // Sync Precomputed data

    reg [DQ_WIDTH-1:0] dq_out;
    reg [DQ_WIDTH-1:0] dq_next1; // Async Precomputed Data
    reg dq_drive; // Controls when the chip drives the DQ

    reg [ROW_BITS-1:0] active_row [0:NUM_BANKS-1];
    reg row_open [0:NUM_BANKS-1];

    wire [ROW_BITS-1:0] row;
    wire [COL_BITS-1:0] col;

    assign row = addr[ROW_POSE-1:COL_POSE];
    assign col = addr[COL_POSE-1:0];
    assign dq = dq_drive ? dq_out : {DQ_WIDTH{1'bz}};

    // Timing
    integer trcd_count, trp_count, cas_delay;
    localparam trcd = 2, trp = 2, tcas = 2;

    // Triple Data Rate
    reg tdr_req;
    reg [2:0] bit_count;

    reg cas_fire;

    reg tdr_mode;

    integer i;
    integer w;
    always @(posedge clk or negedge reset_n) begin
        if (!reset_n) begin
            dq_out <= 0;
            trcd_count <= 0;
            trp_count <= 0;
            cas_delay <= 0;

            for (i = 0; i < NUM_BANKS; i=i+1) begin
                row_open[i] <= 1'b0;
                active_row[i] <= 0;
            end
        end else if (!cs_n) begin
            if (!ras_n && cas_n && we_n) begin // Active CMD
                row_open[ba] <= 1'b1;
                active_row[ba] <= row;
                trcd_count <= trcd; // start timing
            end else if (ras_n && !cas_n && we_n && row_open[ba] && trcd_count == 0) begin // Read CMD
                cas_delay <= tcas;
                dq_drive <= 0;
                bit_count <= 0;
            end else if (ras_n && !cas_n && !we_n && row_open[ba] && trcd_count == 0) begin // Write CMD
                dq_next = mem[{ba, row, col}];
                for (w = 0; w < (DQ_WIDTH/8); w=w+1)
                    if (!dm[w]) 
                        dq_next[w*8 +: 8] = dq[w*8 +: 8];
                mem[{ba, row, col}] <= dq_next;
            end else if (!ras_n && cas_n && !we_n) begin // Precharge CMD
                row_open[ba] <= 1'b0;
                trp_count <= trp;
            end else begin
                dq_drive <= 0;
            end
        end

        if (trcd_count > 0) trcd_count <= trcd_count - 1;
        if (trp_count > 0) trp_count <= trp_count - 1;

        cas_fire <= (cas_delay - 1 == 1);
        tdr_mode <= mddr_n;
        if (cas_delay > 0) begin
            cas_delay <= cas_delay - 1;
        end
    end

    always @(posedge clk or negedge reset_n) begin
        if (!reset_n) begin
            tdr_req <= 0;
            bit_count <= 0;
            dq_drive <= 0;
            async_bs <= 0;
            barm <= 0;
        end else if (cas_fire && row_open[ba]) begin
            dq_drive <= 1;
            dq_out <= mem[{ba, row, col}];
            bit_count <= 1;
            barm <= 1; 
            tdr_req = 1;
        end
    end

    always @(*) begin
        if (cas_fire && tdr_req && reset_n && mddr_n) begin
            dq_next = mem[{ba, row, col + 2'd1}];
            async_bs_next = 1;
            bit_count = 2;
            tdr_req = 0;
        end else if (reset_n && cas_delay == 0 && async_bs_next) begin
            if (backn) begin // Data is Acknowledged
                $display("Bit Ackn @%0t", $time);
                dq_out = dq_next;
                async_bs = async_bs_next;
                async_bs_next = 0;
            end
        end
    end

    always @(negedge clk or negedge reset_n) begin
        if (reset_n && async_bs)
            async_bs <= 0;

        if (!reset_n) begin
            tdr_a <= 0;
            barm <= 0;
        end else if (cas_fire && tdr_mode && backn) begin // TDR Mode
            tdr_a <= 0;

            if (tdr_req == 0 && bit_count > 1) begin // Send bit 3
                bit_count <= 3;
                dq_out <= mem[{ba, row, col + 2'd2}];
                tdr_a <= 1;
                dq_drive <= 0;
            end else begin // DO NOT SEND ANYTHING
                tdr_a <= 0;
                dq_drive <= 0;
            end

            barm <= 0;
        end else if (cas_fire && !tdr_mode) begin // DDR Mode, Send only bit 2
            tdr_a <= 0;
            bit_count <= 2;
            dq_out <= mem[{ba, row, col + 2'd1}];
            dq_drive <= 0;

            barm <= 0;
        end
    end
endmodule

PX-8GVTDR-HR-HDRAM/src/testers/main_t.v
// SPDX-License-Identifier: CERN-OHL-S-2.0
//
// This source file is part of Pheonix-HDRAM
// Licensed under the CERN-OHL-S v2 (https://cern-ohl.web.cern.ch).
// You may redistribute and modify this file under the terms of the CERN-OHL-S v2.

`timescale 1ns/1ps

module tb_px_8gvtdr_hr_hdram #(
    parameter DQ_WIDTH = 16,
    parameter ADDR_WIDTH = 7,
    parameter BANK_WIDTH = 1, // 4 (Final)
    parameter DM_WIDTH = 2,
    parameter NUM_BANKS = (1<<BANK_WIDTH),
    parameter ROW_BITS = 3, // 14 (Final)
    parameter COL_BITS = 4, // 10 (Final)
    parameter ROW_POSE = 7, // Row Position End
    parameter COL_POSE = 4, // Column Position End
    parameter SIM_SIZE = NUM_BANKS*(1<<COL_BITS) // SIM
);

    // Clock with jitter
    reg clk = 0;
    real base_period = 10.0; // 100 MHz
    real jitter;

    always begin
        jitter = ($urandom_range(-300,300)) * 0.001; // +/- 0.3ns
        #(base_period/2.0 + jitter) clk = ~clk;
    end

    // Signals
    reg reset_n;
    reg cs_n, ras_n, cas_n, we_n, cke;
    reg [ADDR_WIDTH-1:0] addr;
    reg [BANK_WIDTH-1:0] ba;
    wire [DQ_WIDTH-1:0] dq;
    reg [DM_WIDTH-1:0] dm;

    wire tdr_a;
    wire async_bs;
    wire bit_arm;
    reg ddr_mode_n;
    reg bit_ackn;

    reg [DQ_WIDTH-1:0] dq_drv;
    reg dq_oe;
    assign dq = dq_oe ? dq_drv : {DQ_WIDTH{1'hz}};

    // DUT
    px_8gvtdr_hr_hdram dut (
        .clk(clk),
        .reset_n(reset_n),
        .cs_n(cs_n),
        .ras_n(ras_n),
        .cas_n(cas_n),
        .we_n(we_n),
        .cke(cke),
        .addr(addr),
        .ba(ba),
        .dq(dq),
        .dm(dm),
        .tdr_a(tdr_a),
        .async_bs(async_bs),
        .barm(bit_arm),
        .mddr_n(ddr_mode_n),
        .backn(bit_ackn)
    );

    // Golden memory
    reg [DQ_WIDTH-1:0] golden_mem [0:SIM_SIZE-1];

    // Reading TDR setup
    reg read_start;
    reg read_done;
    integer read_bursts;
    reg [DQ_WIDTH-1:0] read_samples [0:2];
    reg read_bit_armed;
    reg [BANK_WIDTH-1:0] read_bank;
    reg [COL_BITS-1:0] read_col;

    always @(posedge clk) begin
        $display("Read Start: %0d Read Done: %0d Bit Arm: %0d Read bit armed: %0d @%0t", read_start, read_done, bit_arm, read_bit_armed, $time);
        if (read_start && !read_done) begin
            if (bit_arm && !read_bit_armed) begin
                read_samples[0] = dq;
                bit_ackn = 1;
                read_bit_armed = 1;
                read_bursts = 1;
                $display("Debug: Rising edge burst %0d -> bank=%0d col=%0d data=0x%h @%0t", read_bursts, read_bank, read_col, read_samples[0], $time);
            end
        end
    end

    always @(negedge clk) begin
        if (read_start && !read_done) begin
            if (read_bit_armed && tdr_a) begin
                read_samples[2] = dq;
                bit_ackn = 0;
                read_bit_armed = 0;
                read_bursts = read_bursts + 1;
                read_done = 1;
                $display("Debug: Falling edge burst %0d -> bank=%0d col=%0d data=0x%h mode=TDR @%0t", read_bursts, read_bank, read_col, read_samples[2], $time);
            end else if (read_bit_armed && !tdr_a) begin
                read_bursts = read_bursts + 1;
                read_bit_armed = 0;
                read_done = 1;
                $display("Debug: Falling edge -> bank=%0d col=%0d mode=DDR @%0t", read_bank, read_col, $time);
            end
        end
    end

    always @(*) begin
        if (read_start && !read_done) begin
            if (read_bit_armed && async_bs) begin
                read_samples[1] = dq;
                read_bursts = read_bursts + 1;
                $display("Debug: Async burst 50d -> bank=%0d col=%0d data=0x%h @%0t", read_bursts, read_bank, read_col, read_samples[1], $time);
            end
        end
    end

    // Reset
    initial begin
        reset_n = 0;
        cs_n = 1; ras_n = 1; cas_n = 1; we_n = 1; cke = 1;
        dq_oe = 0; dm = 0; addr = 0; ba = 0;

        repeat (8) @(posedge clk);
        reset_n = 1;
        repeat ($urandom_range(2,10)) @(posedge clk);
    end

    // IC commands
    task activate(input [BANK_WIDTH-1:0] bank, input [ROW_BITS-1:0] row);
        begin
            @(posedge clk);
            ba <= bank;
            addr <= row;
            cs_n <= 0; ras_n <= 0; cas_n <= 1; we_n <= 1;
            @(posedge clk);
            cs_n <= 1; ras_n <= 1;
            $display("Debug: Bank %0d Row %0d has been activated!", bank, row);
        end
    endtask

    task write_mem(input [BANK_WIDTH-1:0] bank, input [ROW_BITS-1:0] row, input [COL_BITS-1:0] col, input [DQ_WIDTH-1:0] data);
        begin
            repeat ($urandom_range(1,3)) @(posedge clk);
            golden_mem[{bank,col}] = data;

            @(posedge clk);
            ba <= bank; addr <= col; cs_n <= 0; ras_n <= 1; cas_n <= 0; we_n <= 0;
            dq_drv <= data; dq_oe <= 1;
            @(posedge clk);
            dq_oe <= 0; cs_n <= 1; cas_n <= 1; we_n <= 1;
            $display("Debug: Written data 0x%h @%0t", data, $time);
        end
    endtask

    task read_mem(input [BANK_WIDTH-1:0] bank, input [ROW_BITS-1:0] row, input [COL_BITS-1:0] col);
        begin
            repeat ($urandom_range(1,4)) @(posedge clk);

            @(posedge clk);
            ba <= bank; addr <= col; cs_n <= 0; ras_n <= 1; cas_n <= 0; we_n <= 1; ddr_mode_n <= 1;
            @(posedge clk);
            cs_n <= 1; cas_n <= 1;

            read_samples[0] = 0;
            read_samples[1] = 0;
            read_samples[2] = 0;
            bit_ackn = 0;
            read_bursts = 0;
            read_bit_armed = 0;
            read_done = 0;
            read_bank = bank;
            read_col = col;
            read_start = 1;

            // Wait for TDR beats
            wait (read_done || read_bursts >= 3);

            read_start = 0;
            read_done = 0;
            bit_ackn = 0;
            read_bursts = 0;
            read_bit_armed = 0;

            if (read_samples[0] !== golden_mem[{bank,row,col}]) begin
                $display("Error: Read mismatch bank=%0d row=%0d col=%0d exp=0x%h got=0x%h @%0t", bank, row, col, golden_mem[{bank,row,col}], read_samples[0], $time);
                $stop;
            end else begin
                $display("Ok: Read bank=%0d col=%0d data=0x%h", bank, col, read_samples[0]);
            end
        end
    endtask

    task precharge(input [BANK_WIDTH-1:0] bank);
        begin
            @(posedge clk);
            ba <= bank; cs_n <= 0; ras_n <= 0; cas_n <= 1; we_n <= 0;
            @(posedge clk);
            cs_n <= 1; ras_n <= 1; we_n <= 1;
        end
    endtask

    // Stress test
    integer i;
    reg [DQ_WIDTH-1:0] data;

    initial begin
        @(posedge reset_n);
        for (i = 0; i < 50; i=i+1) begin
            ba = $urandom_range(0,BANK_WIDTH-1);
            addr = $urandom_range(0,127);
            data = $random;

            activate(ba, addr[ROW_POSE-1:COL_POSE]);
            write_mem(ba, addr[ROW_POSE-1:COL_POSE], addr[COL_POSE-1:0], data);
            read_mem(ba, addr[ROW_POSE-1:COL_POSE], addr[COL_POSE-1:0]);
            precharge(ba);

            repeat ($urandom_range(2,8)) @(posedge clk);
        end
        $display("Success: All Tests Passed!");
        #100 $finish;
    end

    // Waveform
    initial begin
        $dumpfile("tests/waveforms/main_t.vcd");
        $dumpvars(0, tb_px_8gvtdr_hr_hdram);
    end

endmodule

PX-8GVTDR-HR-HDRAM/tests/waveforms/main_t.vcd
$date
	Mon Jan  5 23:14:31 2026
$end
$version
	Icarus Verilog
$end
$timescale
	1ps
$end
$scope module tb_px_8gvtdr_hr_hdram $end
$var wire 16 ! dq [15:0] $end
$var wire 1 " tdr_a $end
$var wire 1 # bit_arm $end
$var wire 1 $ async_bs $end
$var parameter 32 % ADDR_WIDTH $end
$var parameter 32 & BANK_WIDTH $end
$var parameter 32 ' COL_BITS $end
$var parameter 32 ( COL_POSE $end
$var parameter 32 ) DM_WIDTH $end
$var parameter 32 * DQ_WIDTH $end
$var parameter 33 + NUM_BANKS $end
$var parameter 32 , ROW_BITS $end
$var parameter 32 - ROW_POSE $end
$var parameter 69 . SIM_SIZE $end
$var reg 7 / addr [6:0] $end
$var reg 1 0 ba $end
$var reg 1 1 bit_ackn $end
$var reg 1 2 cas_n $end
$var reg 1 3 cke $end
$var reg 1 4 clk $end
$var reg 1 5 cs_n $end
$var reg 16 6 data [15:0] $end
$var reg 1 7 ddr_mode_n $end
$var reg 2 8 dm [1:0] $end
$var reg 16 9 dq_drv [15:0] $end
$var reg 1 : dq_oe $end
$var reg 1 ; ras_n $end
$var reg 1 < read_bank $end
$var reg 1 = read_bit_armed $end
$var reg 4 > read_col [3:0] $end
$var reg 1 ? read_done $end
$var reg 1 @ read_start $end
$var reg 1 A reset_n $end
$var reg 1 B we_n $end
$var real 1 C base_period $end
$var integer 32 D i [31:0] $end
$var real 1 E jitter $end
$var integer 32 F read_bursts [31:0] $end
$scope module dut $end
$var wire 7 G addr [6:0] $end
$var wire 1 0 ba $end
$var wire 1 1 backn $end
$var wire 1 2 cas_n $end
$var wire 1 3 cke $end
$var wire 1 4 clk $end
$var wire 1 5 cs_n $end
$var wire 2 H dm [1:0] $end
$var wire 16 I dq [15:0] $end
$var wire 1 7 mddr_n $end
$var wire 1 ; ras_n $end
$var wire 1 A reset_n $end
$var wire 1 B we_n $end
$var wire 3 J row [2:0] $end
$var wire 4 K col [3:0] $end
$var parameter 32 L ADDR_WIDTH $end
$var parameter 32 M BANK_WIDTH $end
$var parameter 32 N COL_BITS $end
$var parameter 32 O COL_POSE $end
$var parameter 32 P DM_WIDTH $end
$var parameter 32 Q DQ_WIDTH $end
$var parameter 33 R NUM_BANKS $end
$var parameter 32 S ROW_BITS $end
$var parameter 32 T ROW_POSE $end
$var parameter 69 U SIM_SIZE $end
$var parameter 32 V tcas $end
$var parameter 32 W trcd $end
$var parameter 32 X trp $end
$var reg 1 $ async_bs $end
$var reg 1 Y async_bs_next $end
$var reg 1 # barm $end
$var reg 3 Z bit_count [2:0] $end
$var reg 1 [ cas_fire $end
$var reg 1 \ dq_drive $end
$var reg 16 ] dq_next [15:0] $end
$var reg 16 ^ dq_out [15:0] $end
$var reg 1 " tdr_a $end
$var reg 1 _ tdr_mode $end
$var reg 1 ` tdr_req $end
$var integer 32 a cas_delay [31:0] $end
$var integer 32 b i [31:0] $end
$var integer 32 c trcd_count [31:0] $end
$var integer 32 d trp_count [31:0] $end
$var integer 32 e w [31:0] $end
$upscope $end
$scope task activate $end
$var reg 1 f bank $end
$var reg 3 g row [2:0] $end
$upscope $end
$scope task precharge $end
$var reg 1 h bank $end
$upscope $end
$scope task read_mem $end
$var reg 1 i bank $end
$var reg 4 j col [3:0] $end
$var reg 3 k row [2:0] $end
$upscope $end
$scope task write_mem $end
$var reg 1 l bank $end
$var reg 4 m col [3:0] $end
$var reg 16 n data [15:0] $end
$var reg 3 o row [2:0] $end
$upscope $end
$upscope $end
$enddefinitions $end
$comment Show the parameter values. $end
$dumpall
b10 X
b10 W
b10 V
b100000 U
b111 T
b11 S
b10 R
b10000 Q
b10 P
b100 O
b100 N
b1 M
b111 L
b100000 .
b111 -
b11 ,
b10 +
b10000 *
b10 )
b100 (
b100 '
b1 &
b111 %
$end
#0
$dumpvars
bx o
bx n
bx m
xl
bx k
bx j
xi
xh
bx g
xf
bx e
b0 d
b0 c
b10 b
b0 a
0`
x_
b0 ^
bx ]
0\
x[
b0 Z
xY
b0 K
b0 J
bz I
b0 H
b0 G
bx F
r2450863.354 E
bx D
r10 C
1B
0A
x@
x?
bx >
x=
x<
1;
0:
bx 9
b0 8
x7
bx 6
15
04
13
12
x1
00
b0 /
0$
0#
0"
bz !
$end
#2450868354
0[
b10 b
r1082744.598 E
14
#3533617952
r75814.698 E
04
#3609437650
b10 b
r837834.523 E
14
#4447277173
r2260302.59 E
04
#6707584763
b10 b
r3336542.44 E
14
#10044132203
r851608.858 E
04
#10895746061
b10 b
r154620.712 E
14
#11050371773
r2163467.008 E
04
#13213843781
b10 b
r2262289.662 E
14
#15476138443
r3139694.828 E
04
#18615838271
b10 b
r2660093.174 E
14
#21275936445
r4141111 E
04
#25417052445
b10 b
r3324901.096 E
14
#28741958541
r4244498.646 E
04
#32986462187
b10 J
b1010 K
b10 g
0f
b11010100100100 6
b101010 /
b101010 G
b0 D
1A
r1664558.346 E
14
#34651025533
r4071618.265 E
04
#38722648798
b0 J
b10 K
0;
05
b10 /
b10 G
r1003647.767 E
14
#39726301565
r154326.824 E
04
#39880633389
b10 c
1;
15
b11010100100100 n
b10 m
b0 o
0l
r3354188.52 E
14
#43234826909
r1735825.16 E
04
#44970657069
b1 c
r1946188.548 E
14
#46916850617
r1657425.674 E
04
#48574281291
b0 c
r2925021.424 E
14
#51499307715
r1586374.923 E
04
#53085687638
r380328.228 E
14
#53466020866
r849815.322 E
04
#54315841188
b11010100100100 !
b11010100100100 I
1:
b11010100100100 9
0B
02
05
r837772.059 E
14
#55153618247
r2238940.926 E
04
#57392564173
bz !
bz I
1B
12
15
0:
b11010100100100 ]
b10 e
b10 j
b0 k
0i
r1077617.43 E
14
#58470186603
r3581428.963 E
04
#62051620566
r1322044.689 E
14
#63373670255
r1260404.498 E
04
#64634079753
r159627.56 E
14
#64793712313
r112998.697 E
04
#64906716010
r698865.437 E
14
#65605586447
r3047152.878 E
04
#68652744325
17
02
05
r1789274.887 E
14
#70442024212
r18303.787 E
04
#70460332999
1_
b10 a
12
15
1@
b10 >
0<
0?
0=
b0 F
01
r1465270.03 E
14
#71925608029
r2399135.995 E
04
#74324749024
b1 a
1[
r1740993.288 E
14
#76065747312
r2441365.754 E
04
#78507118066
b11010100100100 !
b11010100100100 I
b0 a
0[
1#
b11010100100100 ^
1\
b1 Z
1Y
bx ]
0`
r2231985.406 E
14
#80739108472
r1702038.281 E
04
#82441151753
bx !
bx I
0Y
1$
bx ^
b10 F
1=
11
r506547.489 E
14
#82947704242
0$
0h
01
0@
0?
0=
b0 F
r4184390.871 E
04
#87132100113
0B
0;
05
r3308151.016 E
14
#90440256129
r2697245.429 E
04
#93137506558
b10 d
1B
1;
15
r1816868.103 E
14
#94954379661
r1149899.54 E
04
#96104284201
b1 d
r4123331.8 E
14
#100227621001
r3674367.201 E
04
#103901993202
b0 d
r3813406.942 E
14
#107715405144
r3608482.53 E
04
#111323892674
r1584726.795 E
14
#112908624469
r2500844.793 E
04
#115409474262
r98016.042 E
14
#115507495304
r949468.952 E
04
#116456969256
r3270656.233 E
14
#119727630489
r2817676.53 E
04
#122545312019
r499933.473 E
14
#123045250492
r2634429.174 E
04
#125679684666
b100 J
b101 K
b100 g
b101111010000001 6
b1000101 /
b1000101 G
b1 D
r1059271.446 E
14
#126738961112
r4175010.519 E
04
#130913976631
b0 J
b100 K
0;
05
b100 /
b100 G
r3969665.755 E
14
#134883647386
r2971862.767 E
04
#137855515153
b10 c
1;
15
b101111010000001 n
b100 m
r2788555.507 E
14
#140644075660
r3350831.336 E
04
#143994911996
b1 c
r4235045.078 E
14
#148229962074
r1540186.38 E
04
#149770153454
b0 c
r1338267.408 E
14
#151108425862
r779982.108 E
04
#151888412970
r768327.964 E
14
#152656745934
r3302897.385 E
04
#155959648319
1:
b101111010000001 9
0B
02
05
r615396.127 E
14
#156575049446
r1747140.36 E
04
#158322194806
1B
12
15
0:
b10 e
b100 j
r1811857.671 E
14
#160134057477
r3407949.542 E
04
#163542012019
r2250079.998 E
14
#165792097017
r1630326.538 E
04
#167422428555
02
05
r3830967.518 E
14
#171253401073
r998398.743 E
04
#172251804816
bz !
bz I
b0 Z
0\
b10 a
12
15
b1 F
1=
11
1@
b100 >
r2666720.501 E
14
