PX-8GVTDR-HR-HDRAM/src/main.v
// SPDX-License-Identifier: CERN-OHL-S-2.0
//
// This source file is part of Pheonix-HDRAM
// Licensed under the CERN-OHL-S v2 (https://cern-ohl.web.cern.ch).
// You may redistribute and modify this file under the terms of the CERN-OHL-S v2.

`timescale 1ns/1ps

module px_8gvtdr_hr_hdram #(
    parameter DQ_WIDTH = 16,
    parameter ADDR_WIDTH = 7,
    parameter BANK_WIDTH = 1, // 4 (Final)
    parameter DM_WIDTH = 2,
    parameter NUM_BANKS = (1<<BANK_WIDTH),
    parameter ROW_BITS = 3, // 14 (Final)
    parameter COL_BITS = 4, // 10 (Final)
    parameter ROW_POSE = 7, // Row Position End
    parameter COL_POSE = 4, // Column Position End
    parameter SIM_SIZE = NUM_BANKS*(1<<ROW_BITS)*(1<<COL_BITS) // SIM
) (
    // Clocks
    input wire clk,
    input wire reset_n,

    // Control signals
    input wire cs_n,
    input wire ras_n,
    input wire cas_n,
    input wire we_n,
    input wire cke,
    input wire mddr_n, // Mode Double Data Rate (Active-Low)

    // Address
    input wire [ADDR_WIDTH-1:0] addr,
    input wire [BANK_WIDTH-1:0] ba,

    // Data
    inout wire [DQ_WIDTH-1:0] dq,
    input wire [DM_WIDTH-1:0] dm,
    output reg tdr_a, // TDR Active
    input wire sbt, // Send Bit 3, Controlled internally and externally
    output reg barm // Bit Arm, 1 whenever bits have started being sent, 0 at end of clock cycles
);
    reg [DQ_WIDTH-1:0] mem [0:SIM_SIZE-1];

    reg [DQ_WIDTH-1:0] dq_tmp;
    reg [DQ_WIDTH-1:0] dq_p1;
    reg [DQ_WIDTH-1:0] dq_p2;
    reg [DQ_WIDTH-1:0] dq_p3;
    reg dq_drive; // Controls when the chip drives the DQ
    reg dq_final_drive; // Secondry Control, allows Beat 3 to prevent dq drive and assign

    reg [ROW_BITS-1:0] active_row [0:NUM_BANKS-1];
    reg row_open [0:NUM_BANKS-1];

    wire [ROW_BITS-1:0] row;
    wire [COL_BITS-1:0] col;
    reg [ROW_BITS-1:0] latched_row;
    reg [COL_BITS-1:0] latched_col;
    reg [BANK_WIDTH-1:0] latched_ba;
    assign row = addr[ROW_POSE-1:COL_POSE];
    assign col = addr[COL_POSE-1:0];

    assign dq = (dq_drive && clk) ? // This logic went to crazy, too fast so i added a touch of beauty!
                    !sbt ? 
                        dq_p1
                    : 
                        dq_p2
                :
                    (dq_final_drive && !clk) ?
                        dq_p3
                    :
                        {DQ_WIDTH{1'bz}};

    // Timing
    integer trcd_count, trp_count, cas_delay;
    localparam trcd = 2, trp = 2, tcas = 2;

    // Triple Data Rate
    reg cas_fire;
    wire tdr_mode;
    assign tdr_mode = mddr_n ? 1 : 0;

    integer i;
    integer w;
    always @(posedge clk or negedge reset_n) begin
        if (!reset_n) begin
            dq_p1 <= 0;
            dq_p2 <= 0;
            dq_p3 <= 0;
            trcd_count <= 0;
            trp_count <= 0;
            cas_delay <= 0;
            latched_row <= 0;
            latched_col <= 0;
            latched_ba <= 0;
            dq_final_drive <= 0;

            for (i = 0; i < NUM_BANKS; i=i+1) begin
                row_open[i] <= 1'b0;
                active_row[i] <= 0;
            end
        end else if (!cs_n) begin
            if (!ras_n && cas_n && we_n) begin // Active CMD
                row_open[ba] <= 1'b1;
                active_row[ba] <= row;
                latched_row <= row;
                latched_col <= col;
                latched_ba <= ba;
                trcd_count <= trcd; // start timing
            end else if (ras_n && !cas_n && we_n && row_open[ba] && trcd_count == 0) begin // Read CMD
                cas_delay <= tcas;
                latched_row <= row;
                latched_col <= col;
                latched_ba <= ba;
                dq_drive <= 0;
            end else if (ras_n && !cas_n && !we_n && row_open[ba] && trcd_count == 0) begin // Write CMD
                dq_tmp = mem[{ba, row, col}];
                for (w = 0; w < (DQ_WIDTH/8); w=w+1)
                    if (!dm[w]) 
                        dq_tmp[w*8 +: 8] = dq[w*8 +: 8];
                mem[{ba, row, col}] <= dq_tmp;
            end else if (!ras_n && cas_n && !we_n) begin // Precharge CMD
                row_open[ba] <= 1'b0;
                latched_row <= row;
                latched_col <= col;
                latched_ba <= ba;
                trp_count <= trp;
            end else begin
                dq_drive <= 0;
            end
        end

        if (trcd_count > 0) trcd_count <= trcd_count - 1;
        if (trp_count > 0) trp_count <= trp_count - 1;

        cas_fire <= (cas_delay - 1 == 1);
        if (cas_delay > 0) begin
            cas_delay <= cas_delay - 1;
        end
    end

    always @(posedge clk or negedge reset_n) begin
        if (!reset_n) begin
            dq_drive <= 0;
            barm <= 0;
        end else if (cas_fire && row_open[ba]) begin
            dq_drive <= 1;
            dq_p1 <= mem[{latched_ba, latched_row, latched_col}];
            barm <= 1;
        end
    end

    always @(posedge cas_fire or posedge sbt) begin
        if (cas_fire && tdr_mode && reset_n) begin
            dq_p2 <= mem[{latched_ba, latched_row, latched_col + 2'd1}];
        end
    end

    always @(negedge clk or negedge reset_n) begin
        if (!reset_n) begin
            tdr_a <= 0;
        end else if (cas_fire) begin // TDR Mode
            tdr_a <= tdr_mode ? 1 : 0;
            dq_p3 <= tdr_mode ? mem[{latched_ba, latched_row, latched_col + 2'd2}] : mem[{latched_ba, latched_row, latched_col + 2'd1}];
            dq_drive <= 0;
            dq_final_drive <= 1;
            
            barm <= 0;
        end else begin
            dq_final_drive <= 0;
            tdr_a <= 0;
        end
    end
endmodule

PX-8GVTDR-HR-HDRAM/src/testers/main_t.v
// SPDX-License-Identifier: CERN-OHL-S-2.0
//
// This source file is part of Pheonix-HDRAM
// Licensed under the CERN-OHL-S v2 (https://cern-ohl.web.cern.ch).
// You may redistribute and modify this file under the terms of the CERN-OHL-S v2.

`timescale 1ns/1ps

module tb_px_8gvtdr_hr_hdram #(
    parameter DQ_WIDTH = 16,
    parameter ADDR_WIDTH = 7,
    parameter BANK_WIDTH = 1, // 4 (Final)
    parameter DM_WIDTH = 2,
    parameter NUM_BANKS = (1<<BANK_WIDTH),
    parameter ROW_BITS = 3, // 14 (Final)
    parameter COL_BITS = 4, // 10 (Final)
    parameter ROW_POSE = 7, // Row Position End
    parameter COL_POSE = 4, // Column Position End
    parameter SIM_SIZE = NUM_BANKS*(1<<ROW_BITS)*(1<<COL_BITS) // SIM
);

    // Clock with jitter
    reg clk = 0;
    real base_period = 0.2; // 10.0=100 MHz 1.0=1 GHz 0.2=5GHz
    real jitter;

    always begin
        jitter = ($urandom_range(600) - 300) * 0.001; // +/- 300ps
        #((base_period/2.0) + jitter) clk = ~clk;
    end

    // Signals
    reg reset_n;
    reg cs_n, ras_n, cas_n, we_n, cke;
    reg [ADDR_WIDTH-1:0] addr;
    reg [BANK_WIDTH-1:0] ba;
    wire [DQ_WIDTH-1:0] dq;
    reg [DM_WIDTH-1:0] dm;

    wire tdr_a;
    wire bit_arm;
    reg send_bit_3;
    reg ddr_mode_n;

    reg [DQ_WIDTH-1:0] dq_drv;
    reg dq_oe;
    assign dq = dq_oe ? dq_drv : {DQ_WIDTH{1'hz}};

    // DUT
    px_8gvtdr_hr_hdram dut (
        .clk(clk),
        .reset_n(reset_n),
        .cs_n(cs_n),
        .ras_n(ras_n),
        .cas_n(cas_n),
        .we_n(we_n),
        .cke(cke),
        .addr(addr),
        .ba(ba),
        .dq(dq),
        .dm(dm),
        .tdr_a(tdr_a),
        .barm(bit_arm),
        .mddr_n(ddr_mode_n),
        .sbt(send_bit_3)
    );

    // Golden memory
    reg [DQ_WIDTH-1:0] golden_mem [0:SIM_SIZE-1];

    // Reading TDR setup
    reg read_start;
    reg read_done;
    integer read_bursts;
    reg [DQ_WIDTH-1:0] read_samples [0:2];
    reg read_bit_armed;
    reg [BANK_WIDTH-1:0] read_bank;
    reg [COL_BITS-1:0] read_col;

    always @(posedge clk) begin
        if (read_start && !read_done) begin
            if (bit_arm && !read_bit_armed) begin
                #1;
                read_samples[0] = dq;
                read_bit_armed = 1;
                read_bursts = 1;
                send_bit_3 = 1;
                $display("Debug: Rising edge burst %0d -> bank=%0d col=%0d data=0x%h @%0t", read_bursts, read_bank, read_col, read_samples[0], $time);
            end
        end
    end

    always @(posedge send_bit_3) begin
        if (read_start && !read_done && read_bit_armed && ddr_mode_n) begin
            #1;
            read_samples[1] = dq;
            read_bursts = read_bursts + 1;
            send_bit_3 = 0;
            $display("Debug: Async burst %0d -> bank=%0d col=%0d data=0x%h @%0t", read_bursts, read_bank, read_col, read_samples[1], $time);
        end
    end

    always @(negedge clk) begin
        if (read_start && !read_done && read_bit_armed) begin
            send_bit_3 = 0;
            if (tdr_a) begin
                read_samples[2] = dq;
                read_bit_armed = 0;
                read_bursts = read_bursts + 1;
                read_done = 1;
                $display("Debug: Falling edge burst %0d -> bank=%0d col=%0d data=0x%h mode=TDR @%0t", read_bursts, read_bank, read_col, read_samples[2], $time);
            end else if (!tdr_a) begin
                read_samples[1] = dq;
                read_bursts = read_bursts + 1;
                read_bit_armed = 0;
                read_done = 1;
                $display("Debug: Falling edge -> bank=%0d col=%0d data=0x%h mode=DDR @%0t", read_bank, read_col, read_samples[1], $time);
            end
        end
    end

    // Reset
    initial begin
        reset_n = 0;
        cs_n = 1; ras_n = 1; cas_n = 1; we_n = 1; cke = 1;
        dq_oe = 0; dm = 0; addr = 0; ba = 0;

        repeat (8) @(posedge clk);
        reset_n = 1;
        repeat ($urandom_range(2,10)) @(posedge clk);
    end

    // IC commands
    task activate(input [BANK_WIDTH-1:0] bank, input [ROW_BITS-1:0] row);
        begin
            @(posedge clk);
            ba <= bank;
            addr <= row;
            cs_n <= 0; ras_n <= 0; cas_n <= 1; we_n <= 1;
            @(posedge clk);
            cs_n <= 1; ras_n <= 1;
            $display("Debug: Bank %0d Row %0d has been activated!", bank, row);
        end
    endtask

    task write_mem(input [BANK_WIDTH-1:0] bank, input [ROW_BITS-1:0] row, input [COL_BITS-1:0] col, input [DQ_WIDTH-1:0] data);
        begin
            repeat ($urandom_range(1,3)) @(posedge clk);
            golden_mem[{bank, row, col}] = data;

            @(posedge clk);
            ba <= bank; addr <= col; cs_n <= 0; ras_n <= 1; cas_n <= 0; we_n <= 0;
            dq_drv <= data; dq_oe <= 1;
            @(posedge clk);
            dq_oe <= 0; cs_n <= 1; cas_n <= 1; we_n <= 1;
            $display("Debug: Written data 0x%h @%0t", data, $time);
        end
    endtask

    task read_mem(input [BANK_WIDTH-1:0] bank, input [ROW_BITS-1:0] row, input [COL_BITS-1:0] col);
        begin
            repeat ($urandom_range(1,4)) @(posedge clk);

            @(posedge clk);
            ba <= bank; addr <= col; cs_n <= 0; ras_n <= 1; cas_n <= 0; we_n <= 1; ddr_mode_n <= 1;
            @(posedge clk);
            cs_n <= 1; cas_n <= 1;

            read_samples[0] = 0;
            read_samples[1] = 0;
            read_samples[2] = 0;
            send_bit_3 = 0;
            read_bursts = 0;
            read_bit_armed = 0;
            read_done = 0;
            read_bank = bank;
            read_col = col;
            read_start = 1;

            // Wait for TDR beats
            wait (read_done || read_bursts >= 3);

            read_start = 0;
            read_done = 0;
            send_bit_3 = 0;
            read_bursts = 0;
            read_bit_armed = 0;

            if (read_samples[0] !== golden_mem[{bank,row,col}]) begin
                $display("Error: Read mismatch bank=%0d row=%0d col=%0d exp=0x%h got=0x%h @%0t", bank, row, col, golden_mem[{bank,row,col}], read_samples[0], $time);
                $stop;
            end else begin
                $display("Ok: Read bank=%0d col=%0d data=0x%h", bank, col, read_samples[0]);
            end
        end
    endtask

    task read_mem_tdr(input [BANK_WIDTH-1:0] bank, input [ROW_BITS-1:0] row, input [COL_BITS-1:0] col);
        begin
            repeat ($urandom_range(1,4)) @(posedge clk);

            @(posedge clk);
            ba <= bank; addr <= col; cs_n <= 0; ras_n <= 1; cas_n <= 0; we_n <= 1; ddr_mode_n <= 1;
            @(posedge clk);
            cs_n <= 1; cas_n <= 1;

            read_samples[0] = 0;
            read_samples[1] = 0;
            read_samples[2] = 0;
            send_bit_3 = 0;
            read_bursts = 0;
            read_bit_armed = 0;
            read_done = 0;
            read_bank = bank;
            read_col = col;
            read_start = 1;

            // Wait for TDR beats
            wait (read_done || read_bursts >= 3);

            read_start = 0;
            read_done = 0;
            send_bit_3 = 0;
            read_bursts = 0;
            read_bit_armed = 0;

            if (read_samples[0] !== golden_mem[{bank,row,col}] || read_samples[1] !== golden_mem[{bank,row,col+2'd1}] || read_samples[2] !== golden_mem[{bank,row,col+2'd2}]) begin
                $display("Error: Read mismatch bank=%0d row=%0d col=%0d exp=0x%h%h%h got=0x%h%h%h @%0t", bank, row, col, golden_mem[{bank,row,col}],
                    golden_mem[{bank,row,col+2'd1}], golden_mem[{bank,row,col+2'd2}], read_samples[0], read_samples[1], read_samples[2], $time);
                $stop;
            end else begin
                $display("Ok: Read bank=%0d col=%0d data=0x%h%h%h", bank, col, read_samples[0], read_samples[1], read_samples[2]);
            end
        end
    endtask

    task precharge(input [BANK_WIDTH-1:0] bank);
        begin
            @(posedge clk);
            ba <= bank; cs_n <= 0; ras_n <= 0; cas_n <= 1; we_n <= 0;
            @(posedge clk);
            cs_n <= 1; ras_n <= 1; we_n <= 1;
        end
    endtask

    // Stress test
    integer i;
    reg [DQ_WIDTH-1:0] data;

    initial begin
        @(posedge reset_n);
        for (i = 0; i < 50; i=i+1) begin
            ba = $urandom_range(0,BANK_WIDTH-1);
            addr = $urandom_range(0,127);
            data = $random;

            activate(ba, addr[ROW_POSE-1:COL_POSE]);
            write_mem(ba, addr[ROW_POSE-1:COL_POSE], addr[COL_POSE-1:0], data);
            read_mem(ba, addr[ROW_POSE-1:COL_POSE], addr[COL_POSE-1:0]);
            read_mem_tdr(ba, addr[ROW_POSE-1:COL_POSE], addr[COL_POSE-1:0]);
            precharge(ba);

            repeat ($urandom_range(2,8)) @(posedge clk);
        end
        $display("Success: All Tests Passed!");
        #100 $finish;
    end

    // Waveform
    initial begin
        $dumpfile("tests/waveforms/main_t.vcd");
        $dumpvars(0, tb_px_8gvtdr_hr_hdram);
    end

endmodule

PX-8GVTDR-HR-HDRAM/tests/waveforms/main_t.vcd
$date
	Fri Jan  9 23:37:37 2026
$end
$version
	Icarus Verilog
$end
$timescale
	1ps
$end
$scope module tb_px_8gvtdr_hr_hdram $end
$var wire 16 ! dq [15:0] $end
$var wire 1 " tdr_a $end
$var wire 1 # bit_arm $end
$var parameter 32 $ ADDR_WIDTH $end
$var parameter 32 % BANK_WIDTH $end
$var parameter 32 & COL_BITS $end
$var parameter 32 ' COL_POSE $end
$var parameter 32 ( DM_WIDTH $end
$var parameter 32 ) DQ_WIDTH $end
$var parameter 33 * NUM_BANKS $end
$var parameter 32 + ROW_BITS $end
$var parameter 32 , ROW_POSE $end
$var parameter 104 - SIM_SIZE $end
$var reg 7 . addr [6:0] $end
$var reg 1 / ba $end
$var reg 1 0 cas_n $end
$var reg 1 1 cke $end
$var reg 1 2 clk $end
$var reg 1 3 cs_n $end
$var reg 16 4 data [15:0] $end
$var reg 1 5 ddr_mode_n $end
$var reg 2 6 dm [1:0] $end
$var reg 16 7 dq_drv [15:0] $end
$var reg 1 8 dq_oe $end
$var reg 1 9 ras_n $end
$var reg 1 : read_bank $end
$var reg 1 ; read_bit_armed $end
$var reg 4 < read_col [3:0] $end
$var reg 1 = read_done $end
$var reg 1 > read_start $end
$var reg 1 ? reset_n $end
$var reg 1 @ send_bit_3 $end
$var reg 1 A we_n $end
$var real 1 B base_period $end
$var integer 32 C i [31:0] $end
$var real 1 D jitter $end
$var integer 32 E read_bursts [31:0] $end
$scope module dut $end
$var wire 7 F addr [6:0] $end
$var wire 1 / ba $end
$var wire 1 0 cas_n $end
$var wire 1 1 cke $end
$var wire 1 2 clk $end
$var wire 1 3 cs_n $end
$var wire 2 G dm [1:0] $end
$var wire 16 H dq [15:0] $end
$var wire 1 5 mddr_n $end
$var wire 1 9 ras_n $end
$var wire 1 ? reset_n $end
$var wire 1 @ sbt $end
$var wire 1 A we_n $end
$var wire 1 I tdr_mode $end
$var wire 3 J row [2:0] $end
$var wire 4 K col [3:0] $end
$var parameter 32 L ADDR_WIDTH $end
$var parameter 32 M BANK_WIDTH $end
$var parameter 32 N COL_BITS $end
$var parameter 32 O COL_POSE $end
$var parameter 32 P DM_WIDTH $end
$var parameter 32 Q DQ_WIDTH $end
$var parameter 33 R NUM_BANKS $end
$var parameter 32 S ROW_BITS $end
$var parameter 32 T ROW_POSE $end
$var parameter 104 U SIM_SIZE $end
$var parameter 32 V tcas $end
$var parameter 32 W trcd $end
$var parameter 32 X trp $end
$var reg 1 # barm $end
$var reg 1 Y cas_fire $end
$var reg 1 Z dq_drive $end
$var reg 1 [ dq_final_drive $end
$var reg 16 \ dq_p1 [15:0] $end
$var reg 16 ] dq_p2 [15:0] $end
$var reg 16 ^ dq_p3 [15:0] $end
$var reg 16 _ dq_tmp [15:0] $end
$var reg 1 ` latched_ba $end
$var reg 4 a latched_col [3:0] $end
$var reg 3 b latched_row [2:0] $end
$var reg 1 " tdr_a $end
$var integer 32 c cas_delay [31:0] $end
$var integer 32 d i [31:0] $end
$var integer 32 e trcd_count [31:0] $end
$var integer 32 f trp_count [31:0] $end
$var integer 32 g w [31:0] $end
$upscope $end
$scope task activate $end
$var reg 1 h bank $end
$var reg 3 i row [2:0] $end
$upscope $end
$scope task precharge $end
$var reg 1 j bank $end
$upscope $end
$scope task read_mem $end
$var reg 1 k bank $end
$var reg 4 l col [3:0] $end
$var reg 3 m row [2:0] $end
$upscope $end
$scope task read_mem_tdr $end
$var reg 1 n bank $end
$var reg 4 o col [3:0] $end
$var reg 3 p row [2:0] $end
$upscope $end
$scope task write_mem $end
$var reg 1 q bank $end
$var reg 4 r col [3:0] $end
$var reg 16 s data [15:0] $end
$var reg 3 t row [2:0] $end
$upscope $end
$upscope $end
$enddefinitions $end
$comment Show the parameter values. $end
$dumpall
b10 X
b10 W
b10 V
b100000000 U
b111 T
b11 S
b10 R
b10000 Q
b10 P
b100 O
b100 N
b1 M
b111 L
b100000000 -
b111 ,
b11 +
b10 *
b10000 )
b10 (
b100 '
b100 &
b1 %
b111 $
$end
#0
$dumpvars
bx t
bx s
bx r
xq
bx p
bx o
xn
bx m
bx l
xk
xj
bx i
xh
bx g
b0 f
b0 e
b10 d
b0 c
b0 b
b0 a
0`
bx _
b0 ^
b0 ]
b0 \
0[
0Z
xY
b0 K
b0 J
xI
bz H
b0 G
b0 F
bx E
r0.042 D
bx C
r0.2 B
1A
x@
0?
x>
x=
bx <
x;
x:
19
08
bx 7
b0 6
x5
bx 4
13
02
11
10
0/
b0 .
0#
0"
bz !
$end
#142
0Y
b10 d
r4294967.147 D
12
#4294967389
r4294967.006 D
02
#8589934495
b10 d
r4294967.113 D
12
#12884901708
r0.016 D
02
#12884901824
b10 d
r0.166 D
12
#12884902090
r4294967.115 D
02
#17179869305
b10 d
r4294967.017 D
12
#21474836422
r0.002 D
02
#21474836524
b10 d
r0.016 D
12
#21474836640
r0.139 D
02
#21474836879
b10 d
r0.07200000000000001 D
12
#21474837051
r0.279 D
02
#21474837430
b10 d
r0.165 D
12
#21474837695
r0.293 D
02
#21474838088
b10 J
b1010 K
b10 i
0h
b11010100100100 4
b101010 .
b101010 F
b0 C
1?
r4294967.228 D
12
#25769805416
r0.269 D
02
#25769805785
b0 J
b10 K
09
03
b10 .
b10 F
r4294967.136 D
12
#30064773021
r4294967.017 D
02
#34359740138
b10 e
b10 a
19
13
b11010100100100 s
b10 r
b0 t
0q
r0.169 D
12
#34359740407
r4294967.238 D
02
#38654707745
b1 e
r4294967.268 D
12
#42949675113
r4294967.227 D
02
#47244642440
b0 e
r0.109 D
12
#47244642649
r4294967.217 D
02
#51539609966
r4294967.049 D
12
#55834577115
r4294967.114 D
02
#60129544329
b11010100100100 !
b11010100100100 H
18
b11010100100100 7
0A
00
03
r4294967.113 D
12
#64424511542
r0.013 D
02
#64424511655
bz !
bz H
1A
10
13
08
b11010100100100 _
b10 g
b10 l
b0 m
0k
r4294967.146 D
12
#68719478901
r0.201 D
02
#68719479202
r4294967.18 D
12
#73014446482
r4294967.172 D
02
#77309413754
r4294967.018 D
12
#81604380872
r4294967.011 D
02
#85899347983
r4294967.093 D
12
#90194315176
r0.126 D
02
#90194315402
1I
15
00
03
r4294967.246 D
12
#94489282748
r4294966.998 D
02
#98784249846
b10 c
10
13
1>
b10 <
0:
0=
0;
b0 E
0@
r4294967.201 D
12
#103079217147
r0.035 D
02
#103079217282
bx ]
b1 c
1Y
r4294967.239 D
12
#107374184621
bx !
bx H
1[
bx ^
1"
r0.041 D
02
#107374184762
b0 c
0Y
1#
b11010100100100 \
1Z
b11010100100100 !
b11010100100100 H
r0.012 D
12
#107374184874
0"
0[
bz !
bz H
r4294967.234 D
02
#111669152208
b11010100100100 !
b11010100100100 H
r4294967.066 D
12
#111669153208
bx !
bx H
1@
b1 E
1;
#111669154208
b11010100100100 !
b11010100100100 H
0@
b10 E
#115964119374
bz !
bz H
b10 o
b0 p
0n
0>
0=
0;
b0 E
r0.285 D
02
#115964119759
b11010100100100 !
b11010100100100 H
r0.077 D
12
#115964119936
bz !
bz H
r4294967.25 D
02
#120259087286
b11010100100100 !
b11010100100100 H
r0.141 D
12
#120259087527
bz !
bz H
r4294967.156 D
02
#124554054783
b11010100100100 !
b11010100100100 H
r0.276 D
12
#124554055159
bz !
bz H
r0.214 D
02
#124554055473
b11010100100100 !
b11010100100100 H
r0.233 D
12
#124554055806
bz !
bz H
r0.204 D
02
#124554056110
00
03
b11010100100100 !
b11010100100100 H
r4294967.217 D
12
#128849023427
bz !
bz H
r0.049 D
02
#128849023576
0Z
b10 c
10
13
bz !
bz H
1>
r4294967.009000001 D
12
#133143990685
r4294967.128 D
02
#137438957913
b1 c
1Y
r0.157 D
12
#137438958170
bx !
bx H
0#
1[
1"
r0.094 D
02
#137438958364
1#
1Z
b0 c
0Y
b11010100100100 !
b11010100100100 H
r4294967.065 D
12
#137438958913
bx !
bx H
1@
b1 E
1;
#137438959913
b11010100100100 !
b11010100100100 H
0@
b10 E
